mnfy.py
mnfy-34.0.0.dist-info/DESCRIPTION.rst
mnfy-34.0.0.dist-info/METADATA
mnfy-34.0.0.dist-info/metadata.json
mnfy-34.0.0.dist-info/RECORD
mnfy-34.0.0.dist-info/top_level.txt
mnfy-34.0.0.dist-info/WHEEL
