Metadata-Version: 2.0
Name: mnfy
Version: 34.0.0
Summary: Minify/obfuscate Python 3 source code
Home-page: http://mnfy.rtfd.org/
Author: Brett Cannon
Author-email: brett@python.org
License: Apache Licence 2.0
Platform: UNKNOWN
Classifier: Development Status :: 5 - Production/Stable
Classifier: Intended Audience :: Developers
Classifier: License :: OSI Approved :: Apache Software License
Classifier: Programming Language :: Python :: 3 :: Only
Classifier: Programming Language :: Python :: 3.4
